{
  "type": "FeatureCollection",
  "features": [
    {
      "type": "Feature",
      "properties": {},
      "geometry": {
        "type": "Polygon",
        "coordinates": [
          [
            [
              19.450140595436096,
              51.764516678358966
            ],
            [
              19.45018082857132,
              51.76424941666031
            ],
            [
              19.45089966058731,
              51.76448513824086
            ],
            [
              19.450864791870114,
              51.76459137855084
            ],
            [
              19.450140595436096,
              51.764516678358966
            ]
          ]
        ]
      }
    }
  ]
}